webui/__init__.py
webui/bootstrap.bat
webui/bootstrap.sh
webui/load_library.py
webui/py.typed
webui/webui.py
webui/webui_bindings.py
webui/webui-linux-gcc-arm/libwebui-2.so
webui/webui-linux-gcc-arm64/libwebui-2.so
webui/webui-linux-gcc-x64/libwebui-2.so
webui/webui-macos-clang-arm64/libwebui-2.dylib
webui/webui-macos-clang-x64/libwebui-2.dylib
webui/webui-windows-msvc-x64/webui-2.dll
webui2-2.5.6.dist-info/licenses/LICENSE
webui2-2.5.6.dist-info/METADATA
webui2-2.5.6.dist-info/WHEEL
webui2-2.5.6.dist-info/top_level.txt
webui2-2.5.6.dist-info/RECORD
