Metadata-Version: 2.4
Name: webui2
Version: 2.5.6
Summary: Use any web browser as GUI
Author: Hassan Draga
Project-URL: Homepage, https://github.com/webui-dev/python-webui
Project-URL: Bug Tracker, https://github.com/webui-dev/python-webui/issues
Classifier: Programming Language :: Python :: 3
Classifier: License :: OSI Approved :: MIT License
Classifier: Operating System :: OS Independent
Classifier: Typing :: Typed
Requires-Python: >=3.7
License-File: LICENSE
Dynamic: license-file
